mapper/__init__.py
mapper/__init__.pyi
mapper/flattener.cpp
mapper/main.cpp
mapper/map_module.cpython-311-x86_64-linux-gnu.so
mapper/mapping_fields.cpp
mapper/py.typed
mapper/includes/linux/nlohmann/adl_serializer.hpp
mapper/includes/linux/nlohmann/byte_container_with_subtype.hpp
mapper/includes/linux/nlohmann/json.hpp
mapper/includes/linux/nlohmann/json_fwd.hpp
mapper/includes/linux/nlohmann/ordered_map.hpp
mapper/includes/linux/nlohmann/detail/abi_macros.hpp
mapper/includes/linux/nlohmann/detail/exceptions.hpp
mapper/includes/linux/nlohmann/detail/hash.hpp
mapper/includes/linux/nlohmann/detail/json_custom_base_class.hpp
mapper/includes/linux/nlohmann/detail/json_pointer.hpp
mapper/includes/linux/nlohmann/detail/json_ref.hpp
mapper/includes/linux/nlohmann/detail/macro_scope.hpp
mapper/includes/linux/nlohmann/detail/macro_unscope.hpp
mapper/includes/linux/nlohmann/detail/string_concat.hpp
mapper/includes/linux/nlohmann/detail/string_escape.hpp
mapper/includes/linux/nlohmann/detail/string_utils.hpp
mapper/includes/linux/nlohmann/detail/value_t.hpp
mapper/includes/linux/nlohmann/detail/conversions/from_json.hpp
mapper/includes/linux/nlohmann/detail/conversions/to_chars.hpp
mapper/includes/linux/nlohmann/detail/conversions/to_json.hpp
mapper/includes/linux/nlohmann/detail/input/binary_reader.hpp
mapper/includes/linux/nlohmann/detail/input/input_adapters.hpp
mapper/includes/linux/nlohmann/detail/input/json_sax.hpp
mapper/includes/linux/nlohmann/detail/input/lexer.hpp
mapper/includes/linux/nlohmann/detail/input/parser.hpp
mapper/includes/linux/nlohmann/detail/input/position_t.hpp
mapper/includes/linux/nlohmann/detail/iterators/internal_iterator.hpp
mapper/includes/linux/nlohmann/detail/iterators/iter_impl.hpp
mapper/includes/linux/nlohmann/detail/iterators/iteration_proxy.hpp
mapper/includes/linux/nlohmann/detail/iterators/iterator_traits.hpp
mapper/includes/linux/nlohmann/detail/iterators/json_reverse_iterator.hpp
mapper_lib-1.0.8.dist-info/METADATA
mapper_lib-1.0.8.dist-info/WHEEL
mapper_lib-1.0.8.dist-info/top_level.txt
mapper_lib-1.0.8.dist-info/RECORD
mapper_lib-1.0.8.dist-info/licenses/LICENSE
