Metadata-Version: 2.1
Name: mapper-lib
Version: 1.0.8
Summary: A C++ library for data mapping and transformation
Home-page: https://github.com/compre-sua-peca/csp_mapper
Author: Gustavo de Oliveira
Author-email: Gustavo de Oliveira <devops15@compresuapeca.com.br>
Maintainer-email: Compre Sua Peça <devops4@compresuapeca.com.br>
License: MIT
Project-URL: Homepage, https://github.com/compre-sua-peca/csp_mapper
Project-URL: Repository, https://github.com/compre-sua-peca/csp_mapper
Project-URL: Issues, https://github.com/compre-sua-peca/csp_mapper/issues
Keywords: mapping,data transformation,c++,performance
Classifier: Development Status :: 4 - Beta
Classifier: Intended Audience :: Developers
Classifier: License :: OSI Approved :: MIT License
Classifier: Programming Language :: Python :: 3
Classifier: Programming Language :: Python :: 3.7
Classifier: Programming Language :: Python :: 3.8
Classifier: Programming Language :: Python :: 3.9
Classifier: Programming Language :: Python :: 3.10
Classifier: Programming Language :: Python :: 3.11
Classifier: Programming Language :: C++
Classifier: Topic :: Software Development :: Libraries :: Python Modules
Requires-Python: >=3.7
License-File: LICENSE
Requires-Dist: pybind11>=2.0.0
